[
    {
        "ranking": "200",
        "track": "Lost Cause",
        "year": "2002",
        "artist": "Beck",
        "label": "Universal"
    },
    {
        "ranking": "199",
        "track": "The Rip",
        "year": "2008",
        "artist": "Portishead",
        "label": "Island"
    },
    {
        "ranking": "198",
        "track": "La Rock 01",
        "year": "2001",
        "artist": "Vitalic",
        "label": "International Deejay Gigolo"
    },
    {
        "ranking": "197",
        "track": "Peach, Plum, Pear",
        "year": "2004",
        "artist": "Joanna Newsom",
        "label": "Drag City"
    },
    {
        "ranking": "196",
        "track": "Teen Creeps",
        "year": "2008",
        "artist": "No Age",
        "label": "Sub Pop"
    },
    {
        "ranking": "195",
        "track": "Make Out Fall Out Make Up",
        "year": "2003",
        "artist": "Love Is All",
        "label": "What’s Your Rupture"
    },
    {
        "ranking": "194",
        "track": "Cadillac on 22’s",
        "year": "2003",
        "artist": "David Banner",
        "label": "Universal"
    },
    {
        "ranking": "193",
        "track": "Slow Jamz [ft. Kanye West and Jamie Foxx]",
        "year": "2004",
        "artist": "Twista",
        "label": "Atlantic"
    },
    {
        "ranking": "192",
        "track": "Sunrise",
        "year": "2001",
        "artist": "Pulp",
        "label": "Island"
    },
    {
        "ranking": "191",
        "track": "Oxford Comma",
        "year": "2008",
        "artist": "Vampire Weekend",
        "label": "XL"
    },
    {
        "ranking": "190",
        "track": "Mundian to Bach Ké (Beware of the Boys) [ft. Jay-Z]",
        "year": "2003",
        "artist": "Panjabi MC",
        "label": "Sequence"
    },
    {
        "ranking": "189",
        "track": "Silly Crimes",
        "year": "2006",
        "artist": "The Tough Alliance",
        "label": "Sincerely Yours"
    },
    {
        "ranking": "188",
        "track": "Black Cab",
        "year": "2005",
        "artist": "Jens Lekman",
        "label": "Service/Secretly Canadian"
    },
    {
        "ranking": "187",
        "track": "Mandarine Girl",
        "year": "2005",
        "artist": "Booka Shade",
        "label": "Get Physical"
    },
    {
        "ranking": "186",
        "track": "Cashout",
        "year": "2001",
        "artist": "Fugazi",
        "label": "Dischord"
    },
    {
        "ranking": "185",
        "track": "Hip-Hop",
        "year": "2000",
        "artist": "Dead Prez",
        "label": "Epic/Loud"
    },
    {
        "ranking": "184",
        "track": "No One Knows",
        "year": "2002",
        "artist": "Queens of the Stone Age",
        "label": "Interscope"
    },
    {
        "ranking": "183",
        "track": "Irreplaceable",
        "year": "2006",
        "artist": "Beyoncé",
        "label": "Columbia/Sony"
    },
    {
        "ranking": "182",
        "track": "Our Way to Fall",
        "year": "2000",
        "artist": "Yo La Tengo",
        "label": "Matador"
    },
    {
        "ranking": "181",
        "track": "The First of the Gang to Die",
        "year": "2004",
        "artist": "Morrissey",
        "label": "Attack"
    },
    {
        "ranking": "180",
        "track": "Hollaback Girl",
        "year": "2004",
        "artist": "Gwen Stefani",
        "label": "Interscope"
    },
    {
        "ranking": "179",
        "track": "Skinny Love",
        "year": "2007",
        "artist": "Bon Iver",
        "label": "self-released/Jagjaguwar"
    },
    {
        "ranking": "178",
        "track": "Cherry Blossom Girl",
        "year": "2003",
        "artist": "Air",
        "label": "Source/Astralwerks"
    },
    {
        "ranking": "177",
        "track": "The Real Slim Shady",
        "year": "2000",
        "artist": "Eminem",
        "label": "Aftermath/Interscope"
    },
    {
        "ranking": "176",
        "track": "I Luv the Valley OH!",
        "year": "52004",
        "artist": "Xiu Xiu",
        "label": "RC"
    },
    {
        "ranking": "175",
        "track": "Yeah [ft. Lil Jon and Ludacris]",
        "year": "2003",
        "artist": "Usher",
        "label": "Arista"
    },
    {
        "ranking": "174",
        "track": "You! Me! Dancing!",
        "year": "2007",
        "artist": "Los Campesinos!",
        "label": "Wichita"
    },
    {
        "ranking": "173",
        "track": "Ante Up",
        "year": "2000",
        "artist": "M.O.P.",
        "label": "Loud/Epic"
    },
    {
        "ranking": "172",
        "track": "Prayer to God",
        "year": "2000",
        "artist": "Shellac",
        "label": "Touch and Go"
    },
    {
        "ranking": "171",
        "track": "Get By (Remix) [ft. Mos Def, Jay Z, Kanye West, and Busta Rhymes]",
        "year": "2003",
        "artist": "Talib Kweli",
        "label": "Rawkus"
    },
    {
        "ranking": "170",
        "track": "Trains to Brazil",
        "year": "2005",
        "artist": "Guillemots",
        "label": "Fantastic Plastic/Polydor"
    },
    {
        "ranking": "169",
        "track": "Southern Hospitality",
        "year": "2000",
        "artist": "Ludacris",
        "label": "Def Jam South"
    },
    {
        "ranking": "168",
        "track": "The Past Is a Grotesque Animal",
        "year": "2007",
        "artist": "Of Montreal",
        "label": "Polyvinyl"
    },
    {
        "ranking": "167",
        "track": "The Other Side of Mt. Heart Attack",
        "year": "2006",
        "artist": "Liars",
        "label": "Mute"
    },
    {
        "ranking": "166",
        "track": "Beautiful Life",
        "year": "2007",
        "artist": "Gui Boratto",
        "label": "Kompakt"
    },
    {
        "ranking": "165",
        "track": "The Middle",
        "year": "2001",
        "artist": "Jimmy Eat World",
        "label": "Dreamworks"
    },
    {
        "ranking": "164",
        "track": "Come on Let’s Go",
        "year": "2000",
        "artist": "Broadcast",
        "label": "Warp"
    },
    {
        "ranking": "163",
        "track": "Smash Your Head",
        "year": "2006",
        "artist": "Girl Talk",
        "label": "Illegal Art"
    },
    {
        "ranking": "162",
        "track": "Two Weeks",
        "year": "2009",
        "artist": "Grizzly Bear",
        "label": "Warp"
    },
    {
        "ranking": "161",
        "track": "Dream On [ft. Robyn and Ola Salo]",
        "year": "2006",
        "artist": "Christian Falk",
        "label": "Data/Bonnier Music"
    },
    {
        "ranking": "160",
        "track": "In Da Club",
        "year": "2002",
        "artist": "50 Cent",
        "label": "Aftermath/Interscope"
    },
    {
        "ranking": "159",
        "track": "I Don’t Blame You",
        "year": "2003",
        "artist": "Cat Power",
        "label": "Matador"
    },
    {
        "ranking": "158",
        "track": "Formed a Band",
        "year": "2004",
        "artist": "Art Brut",
        "label": "Rough Trade"
    },
    {
        "ranking": "157",
        "track": "Touch the Sky  [ft. Lupe Fiasco]",
        "year": "2005",
        "artist": "Kanye West",
        "label": "Roc-A-Fella"
    },
    {
        "ranking": "156",
        "track": "Pull Shapes",
        "year": "2006",
        "artist": "The Pipettes",
        "label": "Memphis Industries"
    },
    {
        "ranking": "155",
        "track": "Clocks",
        "year": "2002",
        "artist": "Coldplay",
        "label": "Capitol"
    },
    {
        "ranking": "154",
        "track": "Casimir Pulaski Day",
        "year": "2005",
        "artist": "Sufjan Stevens",
        "label": "Asthmatic Kitty"
    },
    {
        "ranking": "153",
        "track": "Tessio",
        "year": "2000",
        "artist": "Luomo",
        "label": "Force Tracks"
    },
    {
        "ranking": "152",
        "track": "The Leanover",
        "year": "2000",
        "artist": "Life Without Buildings",
        "label": "Tugboat"
    },
    {
        "ranking": "151",
        "track": "L.E.S. Artistes",
        "year": "2008",
        "artist": "Santigold",
        "label": "Downtown"
    },
    {
        "ranking": "150",
        "track": "Move Your Feet",
        "year": "2002",
        "artist": "Junior Senior",
        "label": "Crunchy Frog"
    },
    {
        "ranking": "149",
        "track": "The Crystal Cat",
        "year": "2007",
        "artist": "Dan Deacon",
        "label": "Carpark"
    },
    {
        "ranking": "148",
        "track": "Collapsing at Your Doorstep",
        "year": "2008",
        "artist": "Air France",
        "label": "Sincerely Yours"
    },
    {
        "ranking": "147",
        "track": "Poor Places",
        "year": "2002",
        "artist": "Wilco",
        "label": "Nonesuch/Sundazed"
    },
    {
        "ranking": "146",
        "track": "Caecilia",
        "year": "2001",
        "artist": "Fennesz",
        "label": "Mego"
    },
    {
        "ranking": "145",
        "track": "Cause = Time",
        "year": "2003",
        "artist": "Broken Social Scene",
        "label": "Arts & Crafts"
    },
    {
        "ranking": "144",
        "track": "We Are Your Friends",
        "year": "2003",
        "artist": "Justice vs. Simian",
        "label": "Ed Banger"
    },
    {
        "ranking": "143",
        "track": "1234",
        "year": "2007",
        "artist": "Feist",
        "label": "Cherrytree/Interscope"
    },
    {
        "ranking": "142",
        "track": "Do You Realize??",
        "year": "2002",
        "artist": "The Flaming Lips",
        "label": "Warner Bros."
    },
    {
        "ranking": "141",
        "track": "Toxic",
        "year": "2003",
        "artist": "Britney Spears",
        "label": "Jive"
    },
    {
        "ranking": "140",
        "track": "NYC",
        "year": "2003",
        "artist": "Interpol",
        "label": "Matador"
    },
    {
        "ranking": "139",
        "track": "Harder, Better, Faster, Stronger",
        "year": "2001",
        "artist": "Daft Punk",
        "label": "Virgin"
    },
    {
        "ranking": "138",
        "track": "Untitled (How Does It Feel?)",
        "year": "2000",
        "artist": "D’Angelo",
        "label": "EMI"
    },
    {
        "ranking": "137",
        "track": "Destroy Everything You Touch",
        "year": "2005",
        "artist": "Ladytron",
        "label": "Rykodisc/Island"
    },
    {
        "ranking": "136",
        "track": "Shakey Dog",
        "year": "2006",
        "artist": "Ghostface Killah",
        "label": "Def Jam"
    },
    {
        "ranking": "135",
        "track": "The Modern Age [EP version]",
        "year": "2001",
        "artist": "The Strokes",
        "label": "Rough Trade"
    },
    {
        "ranking": "134",
        "track": "Trill",
        "year": "2006",
        "artist": "Clipse",
        "label": "Jive"
    },
    {
        "ranking": "133",
        "track": "Your Cover’s Blown",
        "year": "2004",
        "artist": "Belle and Sebastian",
        "label": "Rough Trade"
    },
    {
        "ranking": "132",
        "track": "Comfy in Nautica",
        "year": "2005",
        "artist": "Panda Bear",
        "label": "UUAR/Paw Tracks"
    },
    {
        "ranking": "131",
        "track": "Say My Name",
        "year": "2000",
        "artist": "Destiny’s Child",
        "label": "Columbia/Sony"
    },
    {
        "ranking": "130",
        "track": "The Underdog",
        "year": "2007",
        "artist": "Spoon",
        "label": "Anti-"
    },
    {
        "ranking": "129",
        "track": "Party Hard",
        "year": "2001",
        "artist": "Andrew W.K.",
        "label": "Mercury/Island Def Jam"
    },
    {
        "ranking": "128",
        "track": "No Children",
        "year": "42003",
        "artist": "The Mountain Goats",
        "label": "AD"
    },
    {
        "ranking": "127",
        "track": "Oh [ft. Ludacris]",
        "year": "2005",
        "artist": "Ciara",
        "label": "LaFace"
    },
    {
        "ranking": "126",
        "track": "The Orchids",
        "year": "2006",
        "artist": "Califone",
        "label": "Thrill Jockey"
    },
    {
        "ranking": "125",
        "track": "Over the Ice",
        "year": "2006",
        "artist": "The Field",
        "label": "Kompakt"
    },
    {
        "ranking": "124",
        "track": "Where Have All the Rude Boys Gone?",
        "year": "2002",
        "artist": "Ted Leo and the Pharmacists",
        "label": "Lookout!"
    },
    {
        "ranking": "123",
        "track": "Jesus Walks",
        "year": "2004",
        "artist": "Kanye West",
        "label": "Roc-A-Fella"
    },
    {
        "ranking": "122",
        "track": "Hey Ma [ft. Juelz Santana, Freekey Zekey, and Toya]",
        "year": "2002",
        "artist": "Cam’ron",
        "label": "Roc-A-Fella"
    },
    {
        "ranking": "121",
        "track": "You Are the Generation That Bought More Shoes and You Get What You Deserve",
        "year": "2004",
        "artist": "Johnny Boy",
        "label": "Vertigo"
    },
    {
        "ranking": "120",
        "track": "If I Ever Feel Better",
        "year": "2000",
        "artist": "Phoenix",
        "label": "Source/Astralwerks"
    },
    {
        "ranking": "119",
        "track": "Rubber Band Man",
        "year": "2003",
        "artist": "T.I.",
        "label": "Atlantic"
    },
    {
        "ranking": "118",
        "track": "Lloyd, I’m Ready to Be Heartbroken",
        "year": "2006",
        "artist": "Camera Obscura",
        "label": "Elefant/Merge"
    },
    {
        "ranking": "117",
        "track": "Leaf House",
        "year": "2004",
        "artist": "Animal Collective",
        "label": "FatCat"
    },
    {
        "ranking": "116",
        "track": "Dead Leaves and the Dirty Ground",
        "year": "2002",
        "artist": "The White Stripes",
        "label": "Third Man/XL"
    },
    {
        "ranking": "115",
        "track": "Stillness Is the Move",
        "year": "2009",
        "artist": "Dirty Projectors",
        "label": "Domino"
    },
    {
        "ranking": "114",
        "track": "Me and Giuliani Down By the Schoolyard (A True Story)",
        "year": "2003",
        "artist": "!!!",
        "label": "Touch and Go/Warp"
    },
    {
        "ranking": "113",
        "track": "Milkshake",
        "year": "2003",
        "artist": "Kelis",
        "label": "Star Trak/Virgin"
    },
    {
        "ranking": "112",
        "track": "I Feel Space",
        "year": "2005",
        "artist": "Lindstrøm",
        "label": "Playhouse/Feedelity"
    },
    {
        "ranking": "111",
        "track": "We Need a Resolution",
        "year": "2001",
        "artist": "Aaliyah",
        "label": "Virgin"
    },
    {
        "ranking": "110",
        "track": "Fix Up Look Sharp",
        "year": "2003",
        "artist": "Dizzee Rascal",
        "label": "XL/Matador"
    },
    {
        "ranking": "109",
        "track": "Knife",
        "year": "2007",
        "artist": "Grizzly Bear",
        "label": "Warp"
    },
    {
        "ranking": "108",
        "track": "The Swish",
        "year": "2004",
        "artist": "The Hold Steady",
        "label": "Frenchkiss"
    },
    {
        "ranking": "107",
        "track": "Don’t Save Us From the Flames",
        "year": "2005",
        "artist": "M83",
        "label": "Gooom/Mute"
    },
    {
        "ranking": "106",
        "track": "Run to Your Grave",
        "year": "2008",
        "artist": "The Mae Shi",
        "label": "Moshi Moshi"
    },
    {
        "ranking": "105",
        "track": "No Pussy Blues",
        "year": "2007",
        "artist": "Grinderman",
        "label": "Mute"
    },
    {
        "ranking": "104",
        "track": "Lose Yourself",
        "year": "2002",
        "artist": "Eminem",
        "label": "Shady/Interscope"
    },
    {
        "ranking": "103",
        "track": "Mushaboom",
        "year": "2003",
        "artist": "Feist",
        "label": "Polydor"
    },
    {
        "ranking": "102",
        "track": "Hearts on Fire",
        "year": "2007",
        "artist": "Cut Copy",
        "label": "Modular/Island"
    },
    {
        "ranking": "101",
        "track": "So Weit Wie Noch Nie",
        "year": "2002",
        "artist": "Jürgen Paape",
        "label": "Kompakt"
    },
    {
        "ranking": "100",
        "track": "Multiply",
        "year": "2005",
        "artist": "Jamie Lidell",
        "label": "Warp"
    },
    {
        "ranking": "99",
        "track": "Time to Pretend",
        "year": "2008",
        "artist": "MGMT",
        "label": "Columbia"
    },
    {
        "ranking": "98",
        "track": "Postcards From Italy",
        "year": "42006",
        "artist": "Beirut",
        "label": "Ba Da Bing!/AD"
    },
    {
        "ranking": "97",
        "track": "I’m a Cuckoo (by the Avalanches)",
        "year": "2004",
        "artist": "Belle and Sebastian",
        "label": "Rough Trade"
    },
    {
        "ranking": "96",
        "track": "Distortions",
        "year": "2000",
        "artist": "Clinic",
        "label": "Domino"
    },
    {
        "ranking": "95",
        "track": "I’ll Believe in Anything",
        "year": "2005",
        "artist": "Wolf Parade",
        "label": "Sub Pop"
    },
    {
        "ranking": "94",
        "track": "Hounds of Love",
        "year": "6792005",
        "artist": "The Futureheads",
        "label": ""
    },
    {
        "ranking": "93",
        "track": "Hate It or Love It [ft. 50 Cent]",
        "year": "2005",
        "artist": "The Game",
        "label": "Aftermath/Shady/Interscope"
    },
    {
        "ranking": "92",
        "track": "3rd Planet",
        "year": "2000",
        "artist": "Modest Mouse",
        "label": "Epic"
    },
    {
        "ranking": "91",
        "track": "D.A.N.C.E.",
        "year": "2007",
        "artist": "Justice",
        "label": "Because/Ed Banger/Vice"
    },
    {
        "ranking": "90",
        "track": "Weak Become Heroes",
        "year": "6792002",
        "artist": "The Streets",
        "label": ""
    },
    {
        "ranking": "89",
        "track": "Such Great Heights",
        "year": "2003",
        "artist": "The Postal Service",
        "label": "Sub Pop"
    },
    {
        "ranking": "88",
        "track": "Letter From an Occupant",
        "year": "2002",
        "artist": "The New Pornographers",
        "label": "Matador"
    },
    {
        "ranking": "87",
        "track": "Still Tippin’ [ft. Paul Wall and Slim Thug]",
        "year": "2005",
        "artist": "Mike Jones",
        "label": "Asylum/Warner Bros."
    },
    {
        "ranking": "86",
        "track": "To Hell With Good Intentions",
        "year": "2002",
        "artist": "Mclusky",
        "label": "Too Pure"
    },
    {
        "ranking": "85",
        "track": "Long Distance Call",
        "year": "2006",
        "artist": "Phoenix",
        "label": "Source/Virgin"
    },
    {
        "ranking": "84",
        "track": "Young Folks [ft. Victoria Bergsman]",
        "year": "22006",
        "artist": "Peter Bjorn and John",
        "label": "Wichita/V"
    },
    {
        "ranking": "83",
        "track": "Where’s Your Head At?",
        "year": "2001",
        "artist": "Basement Jaxx",
        "label": "XL/Astralwerks"
    },
    {
        "ranking": "82",
        "track": "Be Mine",
        "year": "2005",
        "artist": "Robyn",
        "label": "Konichiwa"
    },
    {
        "ranking": "81",
        "track": "Nothing Ever Happened",
        "year": "42008",
        "artist": "Deerhunter",
        "label": "Kranky/AD"
    },
    {
        "ranking": "80",
        "track": "A Milli",
        "year": "2008",
        "artist": "Lil Wayne",
        "label": "Cash Money"
    },
    {
        "ranking": "79",
        "track": "Izzo (H.O.V.A.)",
        "year": "2001",
        "artist": "Jay-Z",
        "label": "Roc-A-Fella"
    },
    {
        "ranking": "78",
        "track": "A Stroke of Genius",
        "year": "2001",
        "artist": "Freelance Hellraiser",
        "label": "self-released"
    },
    {
        "ranking": "77",
        "track": "Stay Fly",
        "year": "2005",
        "artist": "Three 6 Mafia",
        "label": "Columbia"
    },
    {
        "ranking": "76",
        "track": "Ready for the Floor",
        "year": "2007",
        "artist": "Hot Chip",
        "label": "EMI"
    },
    {
        "ranking": "75",
        "track": "Try Again",
        "year": "2000",
        "artist": "Aaliyah",
        "label": "Virgin"
    },
    {
        "ranking": "74",
        "track": "Silent Shout",
        "year": "2005",
        "artist": "The Knife",
        "label": "Mute"
    },
    {
        "ranking": "73",
        "track": "Grass",
        "year": "2005",
        "artist": "Animal Collective",
        "label": "FatCat"
    },
    {
        "ranking": "72",
        "track": "Mr. Brightside",
        "year": "2003",
        "artist": "The Killers",
        "label": "Universal"
    },
    {
        "ranking": "71",
        "track": "Gone [ft. Consequence and Cam’ron]",
        "year": "2005",
        "artist": "Kanye West",
        "label": "Roc-A-Fella"
    },
    {
        "ranking": "70",
        "track": "In the Morning",
        "year": "2006",
        "artist": "Junior Boys",
        "label": "Domino"
    },
    {
        "ranking": "69",
        "track": "Rebellion (Lies)",
        "year": "2005",
        "artist": "Arcade Fire",
        "label": "Rough Trade"
    },
    {
        "ranking": "68",
        "track": "Forgot About Dre [ft. Eminem]",
        "year": "2000",
        "artist": "Dr. Dre",
        "label": "Aftermath"
    },
    {
        "ranking": "67",
        "track": "The Funeral",
        "year": "2007",
        "artist": "Band of Horses",
        "label": "Kids"
    },
    {
        "ranking": "66",
        "track": "White Winter Hymnal",
        "year": "2008",
        "artist": "Fleet Foxes",
        "label": "Bella Union"
    },
    {
        "ranking": "65",
        "track": "Cry Me a River",
        "year": "2002",
        "artist": "Justin Timberlake",
        "label": "Jive/Media"
    },
    {
        "ranking": "64",
        "track": "Obstacle 1",
        "year": "2002",
        "artist": "Interpol",
        "label": "Matador"
    },
    {
        "ranking": "63",
        "track": "Stuck Between Stations",
        "year": "2006",
        "artist": "The Hold Steady",
        "label": "Vagrant"
    },
    {
        "ranking": "62",
        "track": "New Slang",
        "year": "2001",
        "artist": "The Shins",
        "label": "Sub Pop"
    },
    {
        "ranking": "61",
        "track": "Jesus, Etc.",
        "year": "2002",
        "artist": "Wilco",
        "label": "Nonesuch"
    },
    {
        "ranking": "60",
        "track": "Nutmeg",
        "year": "2000",
        "artist": "Ghostface Killah",
        "label": "Epic"
    },
    {
        "ranking": "59",
        "track": "Pyramid Song",
        "year": "2001",
        "artist": "Radiohead",
        "label": "Capitol"
    },
    {
        "ranking": "58",
        "track": "Fell in Love With a Girl",
        "year": "2002",
        "artist": "The White Stripes",
        "label": "XL"
    },
    {
        "ranking": "57",
        "track": "Wolf Like Me",
        "year": "42006",
        "artist": "TV on the Radio",
        "label": "AD"
    },
    {
        "ranking": "56",
        "track": "I Luv U",
        "year": "2003",
        "artist": "Dizzee Rascal",
        "label": "XL"
    },
    {
        "ranking": "55",
        "track": "Ms. Jackson",
        "year": "2000",
        "artist": "Outkast",
        "label": "LaFace/Arista"
    },
    {
        "ranking": "54",
        "track": "Work It",
        "year": "2002",
        "artist": "Missy Elliott",
        "label": "Elektra"
    },
    {
        "ranking": "53",
        "track": "Someday",
        "year": "2001",
        "artist": "The Strokes",
        "label": "Rough Trade"
    },
    {
        "ranking": "52",
        "track": "Flashing Lights [ft. Dwele]",
        "year": "2007",
        "artist": "Kanye West",
        "label": "Roc-A-Fella"
    },
    {
        "ranking": "51",
        "track": "Takeover",
        "year": "2001",
        "artist": "Jay-Z",
        "label": "Roc-A-Fella"
    },
    {
        "ranking": "50",
        "track": "Romeo",
        "year": "2001",
        "artist": "Basement Jaxx",
        "label": "XL/Astralwerks"
    },
    {
        "ranking": "49",
        "track": "Chicago",
        "year": "2005",
        "artist": "Sufjan Stevens",
        "label": "Asthmatic Kitty"
    },
    {
        "ranking": "48",
        "track": "Bro’s",
        "year": "2006",
        "artist": "Panda Bear",
        "label": "FatCat"
    },
    {
        "ranking": "47",
        "track": "Archangel",
        "year": "2007",
        "artist": "Burial",
        "label": "Hyperdub"
    },
    {
        "ranking": "46",
        "track": "With Every Heartbeat [ft. Kleerup]",
        "year": "2007",
        "artist": "Robyn",
        "label": "Konichiwa/Interscope"
    },
    {
        "ranking": "45",
        "track": "Over and Over",
        "year": "2005",
        "artist": "Hot Chip",
        "label": "DFA/Astralwerks"
    },
    {
        "ranking": "44",
        "track": "Take Me Out",
        "year": "2004",
        "artist": "Franz Ferdinand",
        "label": "Domino"
    },
    {
        "ranking": "43",
        "track": "Int’l Players Anthem (I Choose You) [ft. Outkast]",
        "year": "2007",
        "artist": "UGK",
        "label": "Jive"
    },
    {
        "ranking": "42",
        "track": "Atlas",
        "year": "2007",
        "artist": "Battles",
        "label": "Warp"
    },
    {
        "ranking": "41",
        "track": "Staring at the Sun",
        "year": "2004",
        "artist": "TV on the Radio",
        "label": "Touch and Go"
    },
    {
        "ranking": "40",
        "track": "Since I Left You",
        "year": "2000",
        "artist": "The Avalanches",
        "label": "Modular/XL"
    },
    {
        "ranking": "39",
        "track": "Float On",
        "year": "2004",
        "artist": "Modest Mouse",
        "label": "Epic/Sony"
    },
    {
        "ranking": "38",
        "track": "What You Know",
        "year": "2006",
        "artist": "T.I.",
        "label": "Grand Hustle/Sony"
    },
    {
        "ranking": "37",
        "track": "Can’t Get You Out of My Head",
        "year": "2001",
        "artist": "Kylie Minogue",
        "label": "Parlophone"
    },
    {
        "ranking": "36",
        "track": "Svefn-G-Englar",
        "year": "2000",
        "artist": "Sigur Rós",
        "label": "FatCat/PIAS"
    },
    {
        "ranking": "35",
        "track": "Fireworks",
        "year": "2007",
        "artist": "Animal Collective",
        "label": "Domino"
    },
    {
        "ranking": "34",
        "track": "Galang",
        "year": "2003",
        "artist": "M.I.A.",
        "label": "XL"
    },
    {
        "ranking": "33",
        "track": "The Way We Get By",
        "year": "122003",
        "artist": "Spoon",
        "label": "XU"
    },
    {
        "ranking": "32",
        "track": "1 Thing",
        "year": "2005",
        "artist": "Amerie",
        "label": "Columbia"
    },
    {
        "ranking": "31",
        "track": "Big Pimpin‘ [ft. UGK]",
        "year": "2000",
        "artist": "Jay-Z",
        "label": "Roc-A-Fella"
    },
    {
        "ranking": "30",
        "track": "Seven Nation Army",
        "year": "2003",
        "artist": "The White Stripes",
        "label": "XL"
    },
    {
        "ranking": "29",
        "track": "Boy From School",
        "year": "2006",
        "artist": "Hot Chip",
        "label": "DFA/Astralwerks"
    },
    {
        "ranking": "28",
        "track": "Hope There’s Someone",
        "year": "2005",
        "artist": "Antony and the Johnsons",
        "label": "Secretly Canadian"
    },
    {
        "ranking": "27",
        "track": "Grindin’",
        "year": "2002",
        "artist": "Clipse",
        "label": "Star Trak/Atlantic"
    },
    {
        "ranking": "26",
        "track": "My Love [ft. T.I.]",
        "year": "2006",
        "artist": "Justin Timberlake",
        "label": "Jive"
    },
    {
        "ranking": "25",
        "track": "Umbrella [ft. Jay-Z]",
        "year": "2007",
        "artist": "Rihanna",
        "label": "Def Jam/Universal"
    },
    {
        "ranking": "24",
        "track": "Everything in Its Right Place",
        "year": "2000",
        "artist": "Radiohead",
        "label": "Capitol"
    },
    {
        "ranking": "23",
        "track": "Digital Love",
        "year": "2001",
        "artist": "Daft Punk",
        "label": "Virgin"
    },
    {
        "ranking": "22",
        "track": "Someone Great",
        "year": "2007",
        "artist": "LCD Soundsystem",
        "label": "DFA"
    },
    {
        "ranking": "21",
        "track": "Since U Been Gone",
        "year": "2005",
        "artist": "Kelly Clarkson",
        "label": "RCA"
    },
    {
        "ranking": "20",
        "track": "The Rat",
        "year": "2004",
        "artist": "The Walkmen",
        "label": "Record Collection"
    },
    {
        "ranking": "19",
        "track": "Ignition (Remix)",
        "year": "2002",
        "artist": "R. Kelly",
        "label": "Jive/BMG"
    },
    {
        "ranking": "18",
        "track": "Blind",
        "year": "2008",
        "artist": "Hercules and Love Affair",
        "label": "DFA/Mute"
    },
    {
        "ranking": "17",
        "track": "Heartbeat",
        "year": "6792004",
        "artist": "Annie",
        "label": ""
    },
    {
        "ranking": "16",
        "track": "House of Jealous Lovers",
        "year": "2002",
        "artist": "The Rapture",
        "label": "DFA"
    },
    {
        "ranking": "15",
        "track": "Heartbeats",
        "year": "2002",
        "artist": "The Knife",
        "label": "Rabid/Mute"
    },
    {
        "ranking": "14",
        "track": "99 Problems",
        "year": "2003",
        "artist": "Jay-Z",
        "label": "Roc-A-Fella"
    },
    {
        "ranking": "13",
        "track": "Losing My Edge",
        "year": "2002",
        "artist": "LCD Soundsystem",
        "label": "DFA"
    },
    {
        "ranking": "12",
        "track": "Hey Ya!",
        "year": "2003",
        "artist": "OutKast",
        "label": "LaFace/Arista"
    },
    {
        "ranking": "11",
        "track": "Crazy",
        "year": "2005",
        "artist": "Gnarls Barkley",
        "label": "Downtown/Warner"
    },
    {
        "ranking": "10",
        "track": "Neighborhood #1 (Tunnels)",
        "year": "2004",
        "artist": "Arcade Fire",
        "label": "Merge"
    },
    {
        "ranking": "9",
        "track": "My Girls",
        "year": "2009",
        "artist": "Animal Collective",
        "label": "Domino"
    },
    {
        "ranking": "8",
        "track": "Idioteque",
        "year": "2000",
        "artist": "Radiohead",
        "label": "Capitol"
    },
    {
        "ranking": "7",
        "track": "Get Ur Freak On",
        "year": "2001",
        "artist": "Missy Elliott",
        "label": "Elektra"
    },
    {
        "ranking": "6",
        "track": "Maps",
        "year": "2003",
        "artist": "Yeah Yeah Yeahs",
        "label": "Interscope"
    },
    {
        "ranking": "5",
        "track": "One More Time",
        "year": "2000",
        "artist": "Daft Punk",
        "label": "Virgin"
    },
    {
        "ranking": "4",
        "track": "Crazy in Love [ft. Jay-Z]",
        "year": "2003",
        "artist": "Beyoncé",
        "label": "Columbia/Sony"
    },
    {
        "ranking": "3",
        "track": "Paper Planes (Diplo Remix) [ft. Bun B and Rich Boy]",
        "year": "2007",
        "artist": "M.I.A.",
        "label": "XL/Interscope"
    },
    {
        "ranking": "2",
        "track": "All My Friends",
        "year": "2007",
        "artist": "LCD Soundsystem",
        "label": "DFA/EMI"
    },
    {
        "ranking": "1",
        "track": "B.O.B.",
        "year": "2000",
        "artist": "OutKast",
        "label": "LaFace/Arista"
    }
]